cosma/__init__.py
cosma/__main__.py
cosma-0.3.0.dist-info/WHEEL
cosma-0.3.0.dist-info/entry_points.txt
cosma-0.3.0.dist-info/METADATA
cosma-0.3.0.dist-info/RECORD
