Metadata-Version: 2.4
Name: cosma
Version: 0.3.0
Summary: Search engine for your files!
License-Expression: MIT
Requires-Dist: click-help-colors>=0.9.4
Requires-Dist: cosma-backend
Requires-Dist: cosma-tui
Requires-Python: >=3.12
Project-URL: Homepage, https://github.com/cosmasense/cosma
Project-URL: Issues, https://github.com/cosmasense/cosma/issues
Project-URL: Repository, https://github.com/cosmasense/cosma
